fluke/_cache.py
fluke/_exceptions.py
fluke/_handlers.py
fluke/_helper.py
fluke/_iohandlers.py
fluke/auth.py
fluke/queues.py
fluke/storage.py
fluke_api-0.5.0.dist-info/LICENSE
fluke_api-0.5.0.dist-info/METADATA
fluke_api-0.5.0.dist-info/WHEEL
fluke_api-0.5.0.dist-info/top_level.txt
fluke_api-0.5.0.dist-info/RECORD
