Metadata-Version: 2.1
Name: fluke-api
Version: 0.5.0
Summary: Cloud-agnostic Python API
Author: Manos Stoumpos
Author-email: manosstoumpos@gmail.com
License: MIT
Project-URL: Homepage, https://github.com/manoss96/fluke
Project-URL: Bug Tracker, https://github.com/manoss96/fluke/issues
Project-URL: Documentation, https://fluke.rtfd.io
Project-URL: Changelog, https://github.com/manoss96/fluke/blob/main/CHANGELOG.md
Keywords: cloud,storage,message-queues,aws,azure,gcp
Classifier: Programming Language :: Python :: 3
Classifier: License :: OSI Approved :: MIT License
Classifier: Operating System :: OS Independent
Requires-Python: >=3.9
License-File: LICENSE
Requires-Dist: azure-identity ==1.13.0
Requires-Dist: azure-storage-blob ==12.17.0
Requires-Dist: azure-storage-queue ==12.6.0
Requires-Dist: boto3 ==1.28.0
Requires-Dist: google-cloud-storage ==2.10.0
Requires-Dist: paramiko ==3.2.0
Requires-Dist: tqdm ==4.65.0
Provides-Extra: tests
Requires-Dist: coverage ==7.2.1 ; extra == 'tests'
Requires-Dist: moto[s3,sqs] ==4.1.4 ; extra == 'tests'
